whyml/__init__.py
whyml/api_handlers.py
whyml/caddy.py
whyml/cli.py
whyml/cli_wrapper.py
whyml/converters.py
whyml/exceptions.py
whyml/generators.py
whyml/manifest_loader.py
whyml/manifest_processor.py
whyml/processor.py
whyml/scrapers.py
whyml/server.py
whyml-0.1.28.dist-info/licenses/LICENSE
whyml-cli/tests/__init__.py
whyml-cli/tests/test_cli.py
whyml-cli/tests/test_commands.py
whyml-cli/tests/test_workflows.py
whyml-cli/whyml_cli/__init__.py
whyml-cli/whyml_cli/cli.py
whyml-cli/whyml_cli/main.py
whyml-cli/whyml_cli/commands/__init__.py
whyml-cli/whyml_cli/commands/base_command.py
whyml-cli/whyml_cli/commands/convert_command.py
whyml-cli/whyml_cli/commands/generate_command.py
whyml-cli/whyml_cli/commands/info_command.py
whyml-cli/whyml_cli/commands/scrape_command.py
whyml-cli/whyml_cli/commands/validate_command.py
whyml-converters/tests/__init__.py
whyml-converters/tests/test_html_converter.py
whyml-converters/tests/test_php_converter.py
whyml-converters/tests/test_react_converter.py
whyml-converters/tests/test_vue_converter.py
whyml-converters/whyml_converters/__init__.py
whyml-converters/whyml_converters/base_converter.py
whyml-converters/whyml_converters/conversion_result.py
whyml-converters/whyml_converters/html_converter.py
whyml-converters/whyml_converters/php_converter.py
whyml-converters/whyml_converters/react_converter.py
whyml-converters/whyml_converters/vue_converter.py
whyml-core/tests/__init__.py
whyml-core/tests/test_loading.py
whyml-core/tests/test_processing.py
whyml-core/tests/test_utils.py
whyml-core/tests/test_validation.py
whyml-core/whyml_core/__init__.py
whyml-core/whyml_core/exceptions/__init__.py
whyml-core/whyml_core/exceptions/base_exceptions.py
whyml-core/whyml_core/exceptions/processing_exceptions.py
whyml-core/whyml_core/exceptions/validation_exceptions.py
whyml-core/whyml_core/loading/__init__.py
whyml-core/whyml_core/loading/cache_manager.py
whyml-core/whyml_core/loading/dependency_resolver.py
whyml-core/whyml_core/loading/manifest_loader.py
whyml-0.1.28.dist-info/METADATA
whyml-0.1.28.dist-info/WHEEL
whyml-0.1.28.dist-info/entry_points.txt
whyml-0.1.28.dist-info/top_level.txt
whyml-0.1.28.dist-info/RECORD
