Metadata-Version: 2.4
Name: whyml
Version: 0.1.28
Summary: Advanced YAML-based webpage generator with modular architecture
Author-email: Dynapsys Team <contact@dynapsys.ai>
License: Apache-2.0
Project-URL: Homepage, https://github.com/dynapsys/whyml
Project-URL: Documentation, https://whyml.readthedocs.io
Project-URL: Repository, https://github.com/dynapsys/whyml
Project-URL: Changelog, https://github.com/dynapsys/whyml/releases
Keywords: yaml,manifest,webpage-generator,react,vue,php,html,converter,modular,web-scraper,template-engine,static-site
Classifier: Development Status :: 3 - Alpha
Classifier: Intended Audience :: Developers
Classifier: License :: OSI Approved :: Apache Software License
Classifier: Programming Language :: Python :: 3
Classifier: Programming Language :: Python :: 3.8
Classifier: Programming Language :: Python :: 3.9
Classifier: Programming Language :: Python :: 3.10
Classifier: Programming Language :: Python :: 3.11
Classifier: Programming Language :: Python :: 3.12
Requires-Python: >=3.8
License-File: LICENSE
Requires-Dist: whyml-core>=0.1.0
Requires-Dist: whyml-converters>=0.1.0
Requires-Dist: whyml-scrapers>=0.1.0
Requires-Dist: pyyaml>=6.0
Requires-Dist: aiohttp>=3.8.0
Requires-Dist: aiofiles>=23.0.0
Requires-Dist: jinja2>=3.1.0
Requires-Dist: jsonschema>=4.17.0
Requires-Dist: beautifulsoup4>=4.11.0
Requires-Dist: requests>=2.25.0
Requires-Dist: python-dotenv>=0.19.0
Requires-Dist: pathlib-mate>=1.0.0
Requires-Dist: click>=8.0.0
Requires-Dist: rich>=13.0.0
Requires-Dist: watchdog>=3.0.0
Provides-Extra: cli
Requires-Dist: whyml-cli>=1.0.0; extra == "cli"
Provides-Extra: full
Requires-Dist: whyml-cli>=1.0.0; extra == "full"
Requires-Dist: pillow>=9.0.0; extra == "full"
Requires-Dist: lxml>=4.9.0; extra == "full"
Requires-Dist: selenium>=4.0.0; extra == "full"
Provides-Extra: dev
Requires-Dist: pytest>=6.0.0; extra == "dev"
Requires-Dist: pytest-cov>=2.0.0; extra == "dev"
Requires-Dist: pytest-asyncio>=0.21.0; extra == "dev"
Requires-Dist: black>=22.0.0; extra == "dev"
Requires-Dist: isort>=5.0.0; extra == "dev"
Requires-Dist: mypy>=0.910; extra == "dev"
Requires-Dist: flake8>=4.0.0; extra == "dev"
Requires-Dist: pre-commit>=3.0.0; extra == "dev"
Provides-Extra: test
Requires-Dist: pytest>=6.0.0; extra == "test"
Requires-Dist: pytest-cov>=2.0.0; extra == "test"
Requires-Dist: pytest-asyncio>=0.21.0; extra == "test"
Requires-Dist: pytest-mock>=3.10.0; extra == "test"
Requires-Dist: httpx>=0.24.0; extra == "test"
Dynamic: license-file
